vault2secretsmanager/__init__.py
vault2secretsmanager-0.1.2.dist-info/METADATA
vault2secretsmanager-0.1.2.dist-info/WHEEL
vault2secretsmanager-0.1.2.dist-info/entry_points.txt
vault2secretsmanager-0.1.2.dist-info/top_level.txt
vault2secretsmanager-0.1.2.dist-info/RECORD
