Metadata-Version: 2.1
Name: vault2secretsmanager
Version: 0.1.2
Summary: A systemd service that syncs vault secrets to secrets manager
Home-page: https://github.com/tmb28054/vault2secretsmanager
Author: Topaz M. Bott
Author-email: topaz@topazhome.net
License: Apache License 2.0
Platform: UNKNOWN
Classifier: Development Status :: 5 - Production/Stable
Classifier: Intended Audience :: Developers
Classifier: Natural Language :: English
Classifier: Programming Language :: Python
Classifier: Programming Language :: Python :: 3.9
Classifier: Programming Language :: Python :: 3.10
Classifier: Programming Language :: Python :: 3.11
Requires-Dist: boto3
Requires-Dist: hvac
